bandcamp_auto_uploader/__init__.py
bandcamp_auto_uploader/__main__.py
bandcamp_auto_uploader/bandcamp_http_adapter.py
bandcamp_auto_uploader/config.py
bandcamp_auto_uploader/img/icon.ico
bandcamp_auto_uploader/upload.py
bandcamp_auto_uploader-0.2.15.dist-info/METADATA
bandcamp_auto_uploader-0.2.15.dist-info/WHEEL
bandcamp_auto_uploader-0.2.15.dist-info/entry_points.txt
bandcamp_auto_uploader-0.2.15.dist-info/RECORD
