Metadata-Version: 2.4
Name: bandcamp-auto-uploader
Version: 0.2.15
Summary: Upload albums to Bandcamp automatically without a Pro account
License: MIT
Author: 7x11x13
Author-email: x7x11x13@gmail.com
Requires-Python: >=3.10,<4.0
Classifier: License :: OSI Approved :: MIT License
Classifier: Programming Language :: Python :: 3
Classifier: Programming Language :: Python :: 3.10
Classifier: Programming Language :: Python :: 3.11
Classifier: Programming Language :: Python :: 3.12
Classifier: Programming Language :: Python :: 3.13
Classifier: Programming Language :: Python :: 3.14
Requires-Dist: appdirs (>=1.4.4,<2.0.0)
Requires-Dist: browser-cookie3 (>=0.20.1,<0.21.0)
Requires-Dist: inquirerpy (>=0.3.4,<0.4.0)
Requires-Dist: mutagen (>=1.47.0,<2.0.0)
Requires-Dist: requests (>=2.32.3,<3.0.0)
Requires-Dist: rich (>=13.7.1,<14.0.0)
